tfrecord/__init__.py
tfrecord/example_pb2.py
tfrecord/iterator_utils.py
tfrecord/reader.py
tfrecord/writer.py
tfrecord/tools/__init__.py
tfrecord/tools/tfrecord2idx.py
tfrecord/torch/__init__.py
tfrecord/torch/dataset.py
tfrecord-1.14.4.dist-info/LICENSE
tfrecord-1.14.4.dist-info/METADATA
tfrecord-1.14.4.dist-info/WHEEL
tfrecord-1.14.4.dist-info/top_level.txt
tfrecord-1.14.4.dist-info/RECORD
