Metadata-Version: 2.1
Name: tfrecord
Version: 1.14.4
Summary: TFRecord reader
Home-page: https://github.com/vahidk/tfrecord
Author: Vahid Kazemi
Author-email: vkazemi@gmail.com
License: MIT
License-File: LICENSE
Requires-Dist: numpy
Requires-Dist: protobuf
Requires-Dist: crc32c
